ebcmeasurements/__init__.py
ebcmeasurements/Base/Auxiliary.py
ebcmeasurements/Base/DataLogger.py
ebcmeasurements/Base/DataOutput.py
ebcmeasurements/Base/DataSource.py
ebcmeasurements/Base/DataSourceOutput.py
ebcmeasurements/Base/__init__.py
ebcmeasurements/Beckhoff/AdsDataSourceOutput.py
ebcmeasurements/Beckhoff/__init__.py
ebcmeasurements/Icpdas/IcpdasDataSourceOutput.py
ebcmeasurements/Icpdas/IoBase.py
ebcmeasurements/Icpdas/IoSeries_I87K.py
ebcmeasurements/Icpdas/__init__.py
ebcmeasurements/Mqtt/MqttDataSourceOutput.py
ebcmeasurements/Mqtt/MqttTheThingsNetwork.py
ebcmeasurements/Mqtt/__init__.py
ebcmeasurements/Sensor_Electronic/SensoSysDataSource.py
ebcmeasurements/Sensor_Electronic/SensoSysDevices.py
ebcmeasurements/Sensor_Electronic/__init__.py
EBC_Measurements-1.2.2.dist-info/LICENSE
EBC_Measurements-1.2.2.dist-info/METADATA
EBC_Measurements-1.2.2.dist-info/WHEEL
EBC_Measurements-1.2.2.dist-info/top_level.txt
EBC_Measurements-1.2.2.dist-info/RECORD
