Metadata-Version: 2.1
Name: EBC-Measurements
Version: 1.2.2
Summary: All-in-One Toolbox for Measurement Data Acquisition and Data Logging
Home-page: https://github.com/RWTH-EBC/EBC_Measurements
Author: RWTH Aachen University, E.ON Energy Research Center, Institute for Energy Efficient Buildings and Indoor Climate
Author-email: ebc-tools@eonerc.rwth-aachen.de
License: MIT
Classifier: Programming Language :: Python :: 3
Classifier: License :: OSI Approved :: MIT License
Classifier: Operating System :: OS Independent
Requires-Python: >=3.10
License-File: LICENSE
Requires-Dist: pyserial~=3.5
Requires-Dist: pyads~=3.4.2
Requires-Dist: setuptools~=72.1.0
Requires-Dist: paho-mqtt~=2.1.0
